[{
	"title": "【日本直邮】CASIO 卡西欧 PRO TREK海外版 太阳能男士腕表 PRG-600-1DR",
	"txt": "献给热爱大自然的你",
	"price": "2904",
	"del": "3033",
	"img": "http://pop.nosdn.127.net/74910f3a-721a-468c-980c-7b2c6eefdf9f?imageView&thumbnail=524x0&quality=85",
	"minimg": "http://haitao.nosdn2.127.net/1cc2m9est21_46_46.png?imageView&thumbnail=35x0&quality=85",
	"discount": "9.6折",
	"free": ""
}, {
	"title": "Alpha Industries阿尔法AL186209男士时尚休闲短裤19年夏季新款",
	"txt": "阿尔法男士时尚短裤",
	"price": "689",
	"del": "1298",
	"img": "http://pop.nosdn.127.net/57a073e3-271a-4808-b58a-a11efad2e643?imageView&thumbnail=524x0&quality=85",
	"minimg": "http://haitao.nos.netease.com/1077833fa2854dcb97502084f24f449d1419659976324i46kw8bh10001.png?imageView&thumbnail=35x0&quality=85",
	"discount": "5.4折",
	"free": "包邮"
}, {
	"title": "【日本直邮】JIMMY CHOO 女士简约时尚星星元素长款拉链钱包 filipa cst black",
	"txt": "简约时尚",
	"price": "4839",
	"del": "7573",
	"img": "http://pop.nosdn.127.net/c9ac37a0-139c-4325-a4e5-06d6fad1a0e9?imageView&thumbnail=524x0&quality=85",
	"minimg": "http://haitao.nos.netease.com/7061a236e5c94e64a41446aeb9d3d0a01419662643154i46mhe4x10008.png?imageView&thumbnail=35x0&quality=85",
	"discount": "6.4折",
	"free": ""
}, {
	"title": "GRN 晚用维他命  60粒/瓶 营养精力充沛 增强活力 提升美肤力",
	"txt": "补充维他命和矿物质",
	"price": "138",
	"del": "200",
	"img": "http://pop.nosdn.127.net/4314d47f-887f-4a0e-80ab-851a9b984b25?imageView&thumbnail=524x0&quality=85",
	"minimg": "http://haitao.nosdn1.127.net/c0be3e6c11de4adb9ea90df712da9aea1419662386933i46mbwfo10003.png?imageView&thumbnail=35x0&quality=85",
	"discount": "6.9折",
	"free": ""
}, {
	"title": "博库 胆小别看画系列（共4册）",
	"txt": "胆小别看画系列 ",
	"price": "132",
	"del": "164",
	"img": "http://pop.nosdn.127.net/5b781254-3d1f-46bd-b1d4-8b1845820cae?imageView&thumbnail=524x0&quality=85",
	"minimg": "http://haitao.nosdn2.127.net/iczukrul93.JPG?imageView&thumbnail=35x0&quality=85",
	"discount": "8.1折",
	"free": "包邮"
}, {
	"title": "Mido 美度 Baroncherri 29MM自动上链女装腕表M7600.9.69.1",
	"txt": "轻奢腕表",
	"price": "12038",
	"del": "12038",
	"img": "http://pop.nosdn.127.net/87ae5249-c00f-4b58-ba06-782eaf7adf18?imageView&thumbnail=524x0&quality=85",
	"minimg": "http://haitao.nos.netease.com/369f5f71093f4488921e2e866de7f7cf1419663537993i46n0klk10024.png?imageView&thumbnail=35x0&quality=85",
	"discount": "",
	"free": ""
}, {
	"title": "【日本直邮】Thom Browne 男士时尚休闲领带mnl001a-03560-035",
	"txt": "男士时尚休闲领带",
	"price": "1089",
	"del": "2158",
	"img": "http://pop.nosdn.127.net/98fa02a7-0868-49ba-a6ad-a1f185bbbf09.jpg?imageView&thumbnail=524x0&quality=85",
	"minimg": "http://haitao.nos.netease.com/1077833fa2854dcb97502084f24f449d1419659976324i46kw8bh10001.png?imageView&thumbnail=35x0&quality=85",
	"discount": "5.1折",
	"free": ""
}, {
	"title": "【日本直邮】STELLA McCARTNEY 斯特拉·麦卡特尼 女士时尚简约长款涤纶链条钱包 391835-w9132-4061",
	"txt": "时尚简约",
	"price": "1859",
	"del": "3578",
	"img": "http://pop.nosdn.127.net/c5c9e1ff-4f7f-4350-b4e1-28142108345d.jpg?imageView&thumbnail=524x0&quality=85",
	"minimg": "http://haitao.nos.netease.com/7061a236e5c94e64a41446aeb9d3d0a01419662643154i46mhe4x10008.png?imageView&thumbnail=35x0&quality=85",
	"discount": "5.2折",
	"free": ""
}, {
	"title": "GRN 早用维他命  60粒/瓶 改善气色 精力充沛 体魄增强",
	"txt": "补充身体所需维生素C",
	"price": "138",
	"del": "200",
	"img": "http://pop.nosdn.127.net/ff5c9a54-3fa2-4c51-a381-bb4c468a8e16?imageView&thumbnail=524x0&quality=85",
	"minimg": "http://haitao.nosdn1.127.net/c0be3e6c11de4adb9ea90df712da9aea1419662386933i46mbwfo10003.png?imageView&thumbnail=35x0&quality=85",
	"discount": "6.9折",
	"free": ""
}, {
	"title": "博库 一品芝麻狐+就喜欢你看不惯我又干不掉我的样子（共2册）",
	"txt": "一品芝麻狐喜欢你看不",
	"price": "64",
	"del": "91",
	"img": "http://pop.nosdn.127.net/e4936418-dd64-4224-a4a4-b9d86ab7eae6?imageView&thumbnail=524x0&quality=85",
	"minimg": "http://haitao.nosdn2.127.net/iczukrul93.JPG?imageView&thumbnail=35x0&quality=85",
	"discount": "7.1折",
	"free": "包邮"
}, {
	"title": "LUMINOX 雷美诺时 海军盾牌3500系列手表LUMINOX男士3501全黑色手表",
	"txt": "雷美诺时全黑色手表",
	"price": "2486",
	"del": "2804",
	"img": "http://pop.nosdn.127.net/21d1af3a-70b5-4598-830f-4ae333775e0a.jpg?imageView&thumbnail=524x0&quality=85",
	"minimg": "http://haitao.nos.netease.com/369f5f71093f4488921e2e866de7f7cf1419663537993i46n0klk10024.png?imageView&thumbnail=35x0&quality=85",
	"discount": "8.9折",
	"free": ""
}, {
	"title": "【马克珍妮 法式系列】女童秋装时尚奢华礼服裙 宝宝裙子83088",
	"txt": "优质面料 手感柔软",
	"price": "269",
	"del": "538",
	"img": "http://pop.nosdn.127.net/67ca2aa1-d966-41da-a781-843cc6d8268a?imageView&thumbnail=524x0&quality=85",
	"minimg": "http://haitao.nosdn2.127.net/iczukrul93.JPG?imageView&thumbnail=35x0&quality=85",
	"discount": "5.0折",
	"free": "包邮"
}, {
	"title": "【日本直邮】JIMMY CHOO 男士时尚潮流精美腰包胸包 derry bls black gunmetal",
	"txt": "时尚潮流",
	"price": "7799",
	"del": "12585",
	"img": "http://pop.nosdn.127.net/b477f831-9945-41c1-ad8c-7b310177b9e2?imageView&thumbnail=524x0&quality=85",
	"minimg": "http://haitao.nos.netease.com/7061a236e5c94e64a41446aeb9d3d0a01419662643154i46mhe4x10008.png?imageView&thumbnail=35x0&quality=85",
	"discount": "6.2折",
	"free": ""
}, {
	"title": "GRN红参胶囊加强版  120粒/瓶 ",
	"txt": "强健体魄",
	"price": "428",
	"del": "619",
	"img": "http://pop.nosdn.127.net/252aea50-11fe-4d57-b703-5171562f7764?imageView&thumbnail=524x0&quality=85",
	"minimg": "http://haitao.nosdn1.127.net/c0be3e6c11de4adb9ea90df712da9aea1419662386933i46mbwfo10003.png?imageView&thumbnail=35x0&quality=85",
	"discount": "7.0折",
	"free": ""
}, {
	"title": "博库 我是猫+就喜欢你看不惯我又干不掉我的样子（共2册）",
	"txt": "博库 我是猫",
	"price": "72",
	"del": "85.8",
	"img": "http://pop.nosdn.127.net/d9e70263-0b8f-4bcb-b0c2-4257ed551ecc?imageView&thumbnail=524x0&quality=85",
	"minimg": "http://haitao.nosdn2.127.net/iczukrul93.JPG?imageView&thumbnail=35x0&quality=85",
	"discount": "8.4折",
	"free": "包邮"
}, {
	"title": "【日本直邮】LONGINES 浪琴 嘉岚系列 石英男士腕表 L4.766.2.11.8",
	"txt": "一款具有永恒魅力的设计",
	"price": "15778",
	"del": "15778",
	"img": "http://pop.nosdn.127.net/cc8ef119-68aa-4306-aa8c-fdc50686103d.jpg?imageView&thumbnail=524x0&quality=85",
	"minimg": "http://haitao.nos.netease.com/369f5f71093f4488921e2e866de7f7cf1419663537993i46n0klk10024.png?imageView&thumbnail=35x0&quality=85",
	"discount": "",
	"free": ""
}, {
	"title": "【816定金预付】【热销爆款】MICHAEL KORS 迈克高仕 Jet Set Travel系列 女士单肩手提包",
	"txt": "时尚简约 潮流优雅",
	"price": "848",
	"del": "4000",
	"img": "http://haitao.nos.netease.com/d1f968ab-0d15-4e27-9e92-58804ef3a979_1_1.gif",
	"minimg": "http://haitao.nos.netease.com/1077833fa2854dcb97502084f24f449d1419659976324i46kw8bh10001.png?imageView&thumbnail=35x0&quality=85",
	"discount": "2.2折",
	"free": "包邮"
}, {
	"title": "GUCCI 古驰 男士荔枝皮革短款双Glogo对折钱包钱夹",
	"txt": "GUCCI 男士对折钱包",
	"price": "3059",
	"del": "6120",
	"img": "http://haitao.nos.netease.com/d1f968ab-0d15-4e27-9e92-58804ef3a979_1_1.gif",
	"minimg": "http://haitao.nosdn2.127.net/9ab013a727024145ae377c9a1b6286551419662432571i46mcvne10004.png?imageView&thumbnail=35x0&quality=85",
	"discount": "5.0折",
	"free": "包邮"
}, {
	"title": "VANS万斯 黑色男子百搭休闲鞋运动鞋板鞋VN000SJVPX8",
	"txt": "包裹性 抗冲击 平衡",
	"price": "369",
	"del": "415",
	"img": "http://haitao.nos.netease.com/d1f968ab-0d15-4e27-9e92-58804ef3a979_1_1.gif",
	"minimg": "http://haitao.nos.netease.com/1077833fa2854dcb97502084f24f449d1419659976324i46kw8bh10001.png?imageView&thumbnail=35x0&quality=85",
	"discount": "8.9折",
	"free": "包邮"
}, {
	"title": "礼坊永恒之恋月饼饼干礼盒604g",
	"txt": "月饼礼盒",
	"price": "178",
	"del": "399",
	"img": "http://haitao.nos.netease.com/d1f968ab-0d15-4e27-9e92-58804ef3a979_1_1.gif",
	"minimg": "http://haitao.nosdn1.127.net/939be9ea4d7b4acbb68e67ab531e0d7f1419664531530i46nlv7t10030.png?imageView&thumbnail=35x0&quality=85",
	"discount": "4.5折",
	"free": ""
}, {
	"title": "【大促特价】HAMILTON 汉米尔顿 卡其野战系列机械男表 H70605163",
	"txt": "美式风格 瑞士技术",
	"price": "6574",
	"del": "6574",
	"img": "http://haitao.nos.netease.com/d1f968ab-0d15-4e27-9e92-58804ef3a979_1_1.gif",
	"minimg": "http://haitao.nos.netease.com/1077833fa2854dcb97502084f24f449d1419659976324i46kw8bh10001.png?imageView&thumbnail=35x0&quality=85",
	"discount": "",
	"free": ""
}, {
	"title": "【19新款】MICHAEL KORS 迈克高仕 女士双肩包",
	"txt": "大好时光，Jet Set",
	"price": "1399",
	"del": "4200",
	"img": "http://haitao.nos.netease.com/d1f968ab-0d15-4e27-9e92-58804ef3a979_1_1.gif",
	"minimg": "http://haitao.nos.netease.com/1077833fa2854dcb97502084f24f449d1419659976324i46kw8bh10001.png?imageView&thumbnail=35x0&quality=85",
	"discount": "3.4折",
	"free": "包邮"
}, {
	"title": "PRADA 普拉达 男士黑色织物手拿包",
	"txt": "男士黑色织物手拿包",
	"price": "2359",
	"del": "4720",
	"img": "http://haitao.nos.netease.com/d1f968ab-0d15-4e27-9e92-58804ef3a979_1_1.gif",
	"minimg": "http://haitao.nosdn2.127.net/9ab013a727024145ae377c9a1b6286551419662432571i46mcvne10004.png?imageView&thumbnail=35x0&quality=85",
	"discount": "5.0折",
	"free": "包邮"
}, {
	"title": "【多色选择】Tommy Hilfiger汤米 2019秋冬新款女士圆领长袖抓绒纯色卫衣 美码偏大一码",
	"txt": "内里薄绒 logo标志",
	"price": "529",
	"del": "700",
	"img": "http://haitao.nos.netease.com/d1f968ab-0d15-4e27-9e92-58804ef3a979_1_1.gif",
	"minimg": "http://haitao.nos.netease.com/1077833fa2854dcb97502084f24f449d1419659976324i46kw8bh10001.png?imageView&thumbnail=35x0&quality=85",
	"discount": "7.6折",
	"free": "包邮"
}, {
	"title": "【潮流针织毛线帽】HOTSUIT美国后秀男女 秋冬运动休闲羊毛针织帽棒球帽",
	"txt": "HOTSUIT运动休闲针织帽",
	"price": "229",
	"del": "429",
	"img": "http://haitao.nos.netease.com/d1f968ab-0d15-4e27-9e92-58804ef3a979_1_1.gif",
	"minimg": "http://haitao.nos.netease.com/1077833fa2854dcb97502084f24f449d1419659976324i46kw8bh10001.png?imageView&thumbnail=35x0&quality=85",
	"discount": "5.4折",
	"free": "包邮"
}, {
	"title": "【预售链接】LONGINES 浪琴 瑰丽系列 机械女表 L4.321.4.11.6",
	"txt": "透视表背 独立日期视窗",
	"price": "7599",
	"del": "9100",
	"img": "http://haitao.nos.netease.com/d1f968ab-0d15-4e27-9e92-58804ef3a979_1_1.gif",
	"minimg": "http://haitao.nos.netease.com/369f5f71093f4488921e2e866de7f7cf1419663537993i46n0klk10024.png?imageView&thumbnail=35x0&quality=85",
	"discount": "8.4折",
	"free": "包邮"
}, {
	"title": "Nike Air Force 1 Mid '07 耐克 男子中帮气垫板鞋 ",
	"txt": "经典潮鞋 演绎潮流时尚",
	"price": "796",
	"del": "946",
	"img": "http://haitao.nos.netease.com/d1f968ab-0d15-4e27-9e92-58804ef3a979_1_1.gif",
	"minimg": "http://haitao.nos.netease.com/1077833fa2854dcb97502084f24f449d1419659976324i46kw8bh10001.png?imageView&thumbnail=35x0&quality=85",
	"discount": "8.5折",
	"free": "包邮"
}, {
	"title": "【816同价】Edenus万仟堂 茶杯带过滤380ml办公杯带盖 大容量功夫茶泡茶杯水杯 龙凤呈祥02",
	"txt": "办公家居 便携泡茶",
	"price": "488",
	"del": "488",
	"img": "http://haitao.nos.netease.com/d1f968ab-0d15-4e27-9e92-58804ef3a979_1_1.gif",
	"minimg": "http://haitao.nosdn2.127.net/iczukrul93.JPG?imageView&thumbnail=35x0&quality=85",
	"discount": "",
	"free": ""
}, {
	"title": "FIRSTMIX 2019西装式风衣外套秋季新品绑腰带千鸟格西装外套女",
	"txt": "西装式风衣外套",
	"price": "359",
	"del": "899",
	"img": "http://pop.nosdn.127.net/60595420-f404-4459-a829-ce2c829c91d5?imageView&thumbnail=524x0&quality=85",
	"minimg": "http://haitao.nosdn2.127.net/1cc2m9est21_46_46.png?imageView&thumbnail=35x0&quality=85",
	"discount": "4.0折",
	"free": ""
}, {
	"title": "博库 岁月的智慧(金庸和他的师友们)/人民日报名家写真系列",
	"txt": "岁月的智慧金庸和他的师友",
	"price": "41",
	"del": "48",
	"img": "http://pop.nosdn.127.net/92752379-dce8-4b04-86cd-487729d02270?imageView&thumbnail=524x0&quality=85",
	"minimg": "http://haitao.nosdn2.127.net/iczukrul93.JPG?imageView&thumbnail=35x0&quality=85",
	"discount": "8.6折",
	"free": "包邮"
}, {
	"title": "【日本直邮】HAMILTON 汉米尔顿 瑞士制造爵士经典玫瑰金自动上弦女士手表 H42245191",
	"txt": "至臻精选",
	"price": "8739",
	"del": "8739",
	"img": "http://pop.nosdn.127.net/b9096ac3-914a-4e79-a39c-6ababf593c50?imageView&thumbnail=524x0&quality=85",
	"minimg": "http://haitao.nos.netease.com/1077833fa2854dcb97502084f24f449d1419659976324i46kw8bh10001.png?imageView&thumbnail=35x0&quality=85",
	"discount": "",
	"free": ""
}, {
	"title": "【日本直邮】JIMMY CHOO 男士时尚潮流精美迷彩双肩包 wilmer cin army mix",
	"txt": "时尚潮流",
	"price": "8449",
	"del": "13652",
	"img": "http://pop.nosdn.127.net/584c6bdf-99a7-4838-9e50-7341d65be257?imageView&thumbnail=524x0&quality=85",
	"minimg": "http://haitao.nos.netease.com/7061a236e5c94e64a41446aeb9d3d0a01419662643154i46mhe4x10008.png?imageView&thumbnail=35x0&quality=85",
	"discount": "6.2折",
	"free": ""
}, {
	"title": "HOTSUIT/后秀女卫衣2017冬季新款保暖连帽套头衫户外冬装运动上衣",
	"txt": "日常休闲运动百搭套头衫",
	"price": "449",
	"del": "569",
	"img": "http://pop.nosdn.127.net/fd45ea70-6a9a-438f-b04b-e1a94278761b?imageView&thumbnail=524x0&quality=85",
	"minimg": "http://haitao.nos.netease.com/1077833fa2854dcb97502084f24f449d1419659976324i46kw8bh10001.png?imageView&thumbnail=35x0&quality=85",
	"discount": "7.9折",
	"free": "包邮"
}, {
	"title": "FIRSTMIX  卷边做旧简约长袖针织T恤2019秋季新品女装宽松百搭显瘦圆领套头打底衫女",
	"txt": "卷边做旧简约长袖针织T恤",
	"price": "79",
	"del": "239",
	"img": "http://pop.nosdn.127.net/90edc4fe-25fe-4f40-ad9c-b818527eb70d?imageView&thumbnail=524x0&quality=85",
	"minimg": "http://haitao.nosdn2.127.net/1cc2m9est21_46_46.png?imageView&thumbnail=35x0&quality=85",
	"discount": "3.4折",
	"free": ""
}, {
	"title": "博库 白落梅：陈迹清欢+时光知味（共2册）",
	"txt": "白落梅时光知",
	"price": "56",
	"del": "64",
	"img": "http://pop.nosdn.127.net/b95be577-2389-4610-9a26-22abb9f107c5?imageView&thumbnail=524x0&quality=85",
	"minimg": "http://haitao.nosdn2.127.net/iczukrul93.JPG?imageView&thumbnail=35x0&quality=85",
	"discount": "8.8折",
	"free": "包邮"
}, {
	"title": "【日本直邮】 OMEGA 欧米茄 星座系列 时尚女士石英表腕表女表 123.10.24.60.02.001",
	"txt": "高端大气 优雅魅力",
	"price": "24148",
	"del": "24148",
	"img": "http://pop.nosdn.127.net/1a23c921-56e6-4068-83fe-5f879d3b321c.jpg?imageView&thumbnail=524x0&quality=85",
	"minimg": "http://haitao.nos.netease.com/369f5f71093f4488921e2e866de7f7cf1419663537993i46n0klk10024.png?imageView&thumbnail=35x0&quality=85",
	"discount": "",
	"free": ""
}, {
	"title": "【日本直邮】JIMMY CHOO 男士时尚潮流精美斜挎单肩包 kimi uxi black silver",
	"txt": "时尚潮流",
	"price": "11729",
	"del": "18985",
	"img": "http://haitao.nos.netease.com/d1f968ab-0d15-4e27-9e92-58804ef3a979_1_1.gif",
	"minimg": "http://haitao.nos.netease.com/7061a236e5c94e64a41446aeb9d3d0a01419662643154i46mhe4x10008.png?imageView&thumbnail=35x0&quality=85",
	"discount": "6.2折",
	"free": ""
}, {
	"title": "BRAND'S白兰氏传统鸡精70g*6/盒 进口鸡精提神专注力体力补充精力",
	"txt": "百年历史 提神专注好精神",
	"price": "159",
	"del": "198",
	"img": "http://haitao.nos.netease.com/d1f968ab-0d15-4e27-9e92-58804ef3a979_1_1.gif",
	"minimg": "http://haitao.nosdn2.127.net/41eab3ab43694502a7564ff22e83b6151419663388506i46mxd9510020.png?imageView&thumbnail=35x0&quality=85",
	"discount": "8.1折",
	"free": ""
}, {
	"title": "Mitchell & Ness复古球衣 SW球迷版 NBA魔术队奥尼尔篮球服 透气",
	"txt": "网眼透气 热帖工艺",
	"price": "765",
	"del": "850",
	"img": "http://haitao.nos.netease.com/d1f968ab-0d15-4e27-9e92-58804ef3a979_1_1.gif",
	"minimg": "http://haitao.nos.netease.com/1077833fa2854dcb97502084f24f449d1419659976324i46kw8bh10001.png?imageView&thumbnail=35x0&quality=85",
	"discount": "9.0折",
	"free": "包邮"
}, {
	"title": "博库 亿万星辰不及你 共2册",
	"txt": "亿万星辰不及你 ",
	"price": "64",
	"del": "72.8",
	"img": "http://haitao.nos.netease.com/d1f968ab-0d15-4e27-9e92-58804ef3a979_1_1.gif",
	"minimg": "http://haitao.nosdn2.127.net/iczukrul93.JPG?imageView&thumbnail=35x0&quality=85",
	"discount": "8.8折",
	"free": "包邮"
}, {
	"title": "HAMILTON 汉米尔顿 卡其海军自动机械男表 H78465553",
	"txt": "美式风格 瑞士技术",
	"price": "7609",
	"del": "7820",
	"img": "http://pop.nosdn.127.net/fffd4019-7398-4268-8ca4-d29e67611fad?imageView&thumbnail=524x0&quality=85",
	"minimg": "http://haitao.nos.netease.com/1077833fa2854dcb97502084f24f449d1419659976324i46kw8bh10001.png?imageView&thumbnail=35x0&quality=85",
	"discount": "9.8折",
	"free": ""
}, {
	"title": "【面部专用】SHISEIDO 资生堂 安耐晒 面部专用防晒霜金管 隔离防晒二合一 90ml",
	"txt": "清爽不泛白",
	"price": "193",
	"del": "288",
	"img": "http://pop.nosdn.127.net/1c7e81ee-96b5-4c9e-96e8-54416aa83708?imageView&thumbnail=524x0&quality=85",
	"minimg": "http://haitao.nosdn2.127.net/1cc2m9est21_46_46.png?imageView&thumbnail=35x0&quality=85",
	"discount": "6.8折",
	"free": ""
}, {
	"title": "海德力高蛋白代餐即时奶昔代餐粉蛋白饮膳食纤维饱腹营养食品1箱6瓶装",
	"txt": "新品上市 代餐饱腹",
	"price": "96",
	"del": "169",
	"img": "http://pop.nosdn.127.net/829be049-1762-4766-8abf-ac531b70e124?imageView&thumbnail=524x0&quality=85",
	"minimg": "http://haitao.nos.netease.com/1077833fa2854dcb97502084f24f449d1419659976324i46kw8bh10001.png?imageView&thumbnail=35x0&quality=85",
	"discount": "5.7折",
	"free": ""
}, {
	"title": "【816定金预付】【专柜款】【林允儿同款】MICHAEL KORS 迈克高仕  女士单肩斜挎链条包",
	"txt": "大好时光，Jet Set",
	"price": "1849",
	"del": "4200",
	"img": "http://pop.nosdn.127.net/a48d2b43-f833-4777-8985-c997c4d3eb50?imageView&thumbnail=524x0&quality=85",
	"minimg": "http://haitao.nos.netease.com/1077833fa2854dcb97502084f24f449d1419659976324i46kw8bh10001.png?imageView&thumbnail=35x0&quality=85",
	"discount": "4.5折",
	"free": "包邮"
}, {
	"title": "博库 亿万星辰不及你(共3册)",
	"txt": "亿万星辰不及你 ",
	"price": "88",
	"del": "110.8",
	"img": "http://pop.nosdn.127.net/0183e0a2-52d0-46e7-858a-7f70609849c8?imageView&thumbnail=524x0&quality=85",
	"minimg": "http://haitao.nosdn2.127.net/iczukrul93.JPG?imageView&thumbnail=35x0&quality=85",
	"discount": "8.0折",
	"free": "包邮"
}, {
	"title": "【惊喜4小时】CASIO 卡西欧简约经典 数字显示 中性手表 dw-6900lu-8dr",
	"txt": "至臻之选",
	"price": "989",
	"del": "989",
	"img": "http://pop.nosdn.127.net/96c9ac68-0268-4473-8443-1633ecd73a22?imageView&thumbnail=524x0&quality=85",
	"minimg": "http://haitao.nosdn2.127.net/1cc2m9est21_46_46.png?imageView&thumbnail=35x0&quality=85",
	"discount": "",
	"free": ""
}, {
	"title": "【马克珍妮 法式系列】女童秋装羊毛混纺背带裙 宝宝裙子83039",
	"txt": "咖白格纹 简约时尚",
	"price": "139",
	"del": "278",
	"img": "http://pop.nosdn.127.net/255d393b-6c9a-4f15-9fd3-88190a3e5e49?imageView&thumbnail=524x0&quality=85",
	"minimg": "http://haitao.nosdn2.127.net/iczukrul93.JPG?imageView&thumbnail=35x0&quality=85",
	"discount": "5.0折",
	"free": "包邮"
}, {
	"title": "GRN 小绿 绿茶儿茶素片 健康减重 60粒/瓶",
	"txt": "绿色减脂  燃烧卡路里 ",
	"price": "207",
	"del": "300",
	"img": "http://pop.nosdn.127.net/84928e99-a917-4ccd-bd77-9c0d1d5b6df4?imageView&thumbnail=524x0&quality=85",
	"minimg": "http://haitao.nosdn1.127.net/c0be3e6c11de4adb9ea90df712da9aea1419662386933i46mbwfo10003.png?imageView&thumbnail=35x0&quality=85",
	"discount": "6.9折",
	"free": ""
}, {
	"title": "博库 时光倒流的女孩+岛上书店+玛格丽特小镇",
	"txt": "时光倒流的女孩 ",
	"price": "83",
	"del": "109",
	"img": "http://haitao.nos.netease.com/d1f968ab-0d15-4e27-9e92-58804ef3a979_1_1.gif",
	"minimg": "http://haitao.nosdn2.127.net/iczukrul93.JPG?imageView&thumbnail=35x0&quality=85",
	"discount": "7.7折",
	"free": "包邮"
}, {
	"title": "【无税费】Kiehl's 科颜氏 维C紧致亮肤精华液5ml*3",
	"txt": "紧致轮廓，对抗暗黄",
	"price": "195",
	"del": "195",
	"img": "http://haitao.nos.netease.com/d1f968ab-0d15-4e27-9e92-58804ef3a979_1_1.gif",
	"minimg": "http://haitao.nos.netease.com/1077833fa2854dcb97502084f24f449d1419659976324i46kw8bh10001.png?imageView&thumbnail=35x0&quality=85",
	"discount": "",
	"free": ""
}, {
	"title": "【日本直邮】TORY BURCH 汤丽柏琦 女士蓝色长款钱包卡包皮革 50352 403 BEAU",
	"txt": "时尚百搭",
	"price": "1409",
	"del": "2841",
	"img": "http://haitao.nos.netease.com/d1f968ab-0d15-4e27-9e92-58804ef3a979_1_1.gif",
	"minimg": "http://haitao.nos.netease.com/1077833fa2854dcb97502084f24f449d1419659976324i46kw8bh10001.png?imageView&thumbnail=35x0&quality=85",
	"discount": "5.0折",
	"free": ""
}, {
	"title": "【日本直邮】CRUNA 男士优雅传统意大利式风格T恤DOWNTOWN-327",
	"txt": "时尚休闲",
	"price": "669",
	"del": "1318",
	"img": "http://haitao.nos.netease.com/d1f968ab-0d15-4e27-9e92-58804ef3a979_1_1.gif",
	"minimg": "http://haitao.nosdn2.127.net/9ab013a727024145ae377c9a1b6286551419662432571i46mcvne10004.png?imageView&thumbnail=35x0&quality=85",
	"discount": "5.1折",
	"free": ""
}, {
	"title": "【日本直邮】EMPORIO ARMANI 安普里奥·阿玛尼 男士商务斜条纹领带340075-8A308-00020",
	"txt": "时尚休闲",
	"price": "679",
	"del": "1441",
	"img": "http://haitao.nos.netease.com/d1f968ab-0d15-4e27-9e92-58804ef3a979_1_1.gif",
	"minimg": "http://haitao.nosdn2.127.net/9ab013a727024145ae377c9a1b6286551419662432571i46mcvne10004.png?imageView&thumbnail=35x0&quality=85",
	"discount": "4.8折",
	"free": ""
}, {
	"title": "博库 经典名著口碑版本系列 共7册",
	"txt": "经典名著口碑版本系列 ",
	"price": "143",
	"del": "214",
	"img": "http://haitao.nos.netease.com/d1f968ab-0d15-4e27-9e92-58804ef3a979_1_1.gif",
	"minimg": "http://haitao.nosdn2.127.net/iczukrul93.JPG?imageView&thumbnail=35x0&quality=85",
	"discount": "6.7折",
	"free": "包邮"
}, {
	"title": "ESTĒE LAUDER 雅诗兰黛 晶透净颜洁面乳 30毫升*3只装",
	"txt": "净透净颜 唤醒美肌",
	"price": "252",
	"del": "252",
	"img": "http://haitao.nos.netease.com/d1f968ab-0d15-4e27-9e92-58804ef3a979_1_1.gif",
	"minimg": "http://haitao.nos.netease.com/1077833fa2854dcb97502084f24f449d1419659976324i46kw8bh10001.png?imageView&thumbnail=35x0&quality=85",
	"discount": "",
	"free": ""
}, {
	"title": "【日本直邮】VALENTINO 华伦天奴 男士钱包零钱包黑色qy2p0p85tfn-0no",
	"txt": "经典百搭",
	"price": "1729",
	"del": "3488",
	"img": "http://haitao.nos.netease.com/d1f968ab-0d15-4e27-9e92-58804ef3a979_1_1.gif",
	"minimg": "http://haitao.nosdn2.127.net/9ab013a727024145ae377c9a1b6286551419662432571i46mcvne10004.png?imageView&thumbnail=35x0&quality=85",
	"discount": "5.0折",
	"free": ""
}, {
	"title": "【816定金预付】【19春夏新款】PINKO 品高 女士宽肩带珠花精致燕子包单肩斜挎包",
	"txt": "曼妙多姿 少女标配",
	"price": "1849",
	"del": "4500",
	"img": "http://haitao.nos.netease.com/d1f968ab-0d15-4e27-9e92-58804ef3a979_1_1.gif",
	"minimg": "http://haitao.nosdn2.127.net/9ab013a727024145ae377c9a1b6286551419662432571i46mcvne10004.png?imageView&thumbnail=35x0&quality=85",
	"discount": "4.2折",
	"free": "包邮"
}, {
	"title": "【日本直邮】FINAMORE 男士商务水滴图案领带咖啡色ANVERSA3-570001-04",
	"txt": "时尚休闲",
	"price": "679",
	"del": "1441",
	"img": "http://haitao.nos.netease.com/d1f968ab-0d15-4e27-9e92-58804ef3a979_1_1.gif",
	"minimg": "http://haitao.nosdn2.127.net/9ab013a727024145ae377c9a1b6286551419662432571i46mcvne10004.png?imageView&thumbnail=35x0&quality=85",
	"discount": "4.8折",
	"free": ""
}, {
	"title": "博库 艾青诗选&水浒传 共3册",
	"txt": "艾青诗选水浒传 共3册",
	"price": "82",
	"del": "109.6",
	"img": "http://haitao.nos.netease.com/d1f968ab-0d15-4e27-9e92-58804ef3a979_1_1.gif",
	"minimg": "http://haitao.nosdn2.127.net/iczukrul93.JPG?imageView&thumbnail=35x0&quality=85",
	"discount": "7.5折",
	"free": "包邮"
}, {
	"title": "LANCÔME兰蔻 肌底修护舒润精华液 小黑瓶 4ml*3（小安瓶）",
	"txt": "平滑舒缓，弹润去黄",
	"price": "415",
	"del": "415",
	"img": "http://haitao.nos.netease.com/d1f968ab-0d15-4e27-9e92-58804ef3a979_1_1.gif",
	"minimg": "http://haitao.nosdn1.127.net/d3c18d60f0e54c32af5cf24d18be585b1419662519909i46mer1g10007.png?imageView&thumbnail=35x0&quality=85",
	"discount": "",
	"free": ""
}, {
	"title": "【日本直邮】FURLA 芙拉 女士休闲时尚潮流纯色三折钱包PU28-OAV-O60",
	"txt": "时尚休闲",
	"price": "679",
	"del": "1635",
	"img": "http://haitao.nos.netease.com/d1f968ab-0d15-4e27-9e92-58804ef3a979_1_1.gif",
	"minimg": "http://haitao.nosdn2.127.net/9ab013a727024145ae377c9a1b6286551419662432571i46mcvne10004.png?imageView&thumbnail=35x0&quality=85",
	"discount": "4.2折",
	"free": ""
}, {
	"title": "【日本直邮】JIMMY CHOO 经典百搭女士真皮星星手提包米色中号sofia-m-emg-musk",
	"txt": "经典百搭",
	"price": "",
	"del": "",
	"img": "http://haitao.nos.netease.com/d1f968ab-0d15-4e27-9e92-58804ef3a979_1_1.gif",
	"minimg": "http://haitao.nos.netease.com/7061a236e5c94e64a41446aeb9d3d0a01419662643154i46mhe4x10008.png?imageView&thumbnail=35x0&quality=85",
	"discount": "",
	"free": ""
}, {
	"title": "【日本直邮】ETRO 男士时尚商务藏青色丝绸领带 12026-3150-0500",
	"txt": "时尚商务",
	"price": "629",
	"del": "1181",
	"img": "http://haitao.nos.netease.com/d1f968ab-0d15-4e27-9e92-58804ef3a979_1_1.gif",
	"minimg": "http://haitao.nosdn2.127.net/1cc2m9est21_46_46.png?imageView&thumbnail=35x0&quality=85",
	"discount": "5.4折",
	"free": ""
}, {
	"title": "【816定金预付】COACH 蔻驰 男士大号单肩手提公文包",
	"txt": "纽约高街双C经典印花气质",
	"price": "1399",
	"del": "6000",
	"img": "http://haitao.nos.netease.com/d1f968ab-0d15-4e27-9e92-58804ef3a979_1_1.gif",
	"minimg": "http://haitao.nos.netease.com/1077833fa2854dcb97502084f24f449d1419659976324i46kw8bh10001.png?imageView&thumbnail=35x0&quality=85",
	"discount": "2.4折",
	"free": "包邮"
}, {
	"title": "博库 江山美人谋套装 共4册",
	"txt": "江山美人谋套装 共4册",
	"price": "78",
	"del": "99.6",
	"img": "http://haitao.nos.netease.com/d1f968ab-0d15-4e27-9e92-58804ef3a979_1_1.gif",
	"minimg": "http://haitao.nosdn2.127.net/iczukrul93.JPG?imageView&thumbnail=35x0&quality=85",
	"discount": "7.9折",
	"free": "包邮"
}, {
	"title": "【日本直邮】TORY BURCH 汤丽柏琦 女士经典流行2折卡包钱包 52703 612",
	"txt": "经典百搭",
	"price": "789",
	"del": "1647",
	"img": "http://haitao.nos.netease.com/d1f968ab-0d15-4e27-9e92-58804ef3a979_1_1.gif",
	"minimg": "http://haitao.nos.netease.com/1077833fa2854dcb97502084f24f449d1419659976324i46kw8bh10001.png?imageView&thumbnail=35x0&quality=85",
	"discount": "4.8折",
	"free": ""
}, {
	"title": "【日本直邮】BALENCIAGA 巴黎世家 女士时尚潮流经典舒适运动鞋 524039 w09oh 647",
	"txt": "时尚潮流",
	"price": "5889",
	"del": "9364",
	"img": "http://haitao.nos.netease.com/d1f968ab-0d15-4e27-9e92-58804ef3a979_1_1.gif",
	"minimg": "http://haitao.nosdn1.127.net/d3c18d60f0e54c32af5cf24d18be585b1419662519909i46mer1g10007.png?imageView&thumbnail=35x0&quality=85",
	"discount": "6.3折",
	"free": ""
}, {
	"title": "【日本直邮】Finamore 男士时尚简约米色条纹商务丝绸领带 anversa8-330012-4",
	"txt": "时尚简约",
	"price": "",
	"del": "",
	"img": "http://haitao.nos.netease.com/d1f968ab-0d15-4e27-9e92-58804ef3a979_1_1.gif",
	"minimg": "http://haitao.nosdn2.127.net/9ab013a727024145ae377c9a1b6286551419662432571i46mcvne10004.png?imageView&thumbnail=35x0&quality=85",
	"discount": "",
	"free": ""
}, {
	"title": "【816定金预付】COACH 蔻驰 Tote系列女士单肩手提包 中号拉链款logo印花托特包",
	"txt": "经典老印花百搭大气",
	"price": "855",
	"del": "3000",
	"img": "http://haitao.nos.netease.com/d1f968ab-0d15-4e27-9e92-58804ef3a979_1_1.gif",
	"minimg": "http://haitao.nos.netease.com/1077833fa2854dcb97502084f24f449d1419659976324i46kw8bh10001.png?imageView&thumbnail=35x0&quality=85",
	"discount": "2.9折",
	"free": "包邮"
}, {
	"title": "【日本直邮】EMPORIO ARMANI 安普里奥·阿玛尼 男士时尚简约潮流长款两折钱包YEM474-YC043-80001",
	"txt": "时尚休闲",
	"price": "1089",
	"del": "2146",
	"img": "http://haitao.nos.netease.com/d1f968ab-0d15-4e27-9e92-58804ef3a979_1_1.gif",
	"minimg": "http://haitao.nosdn2.127.net/9ab013a727024145ae377c9a1b6286551419662432571i46mcvne10004.png?imageView&thumbnail=35x0&quality=85",
	"discount": "5.1折",
	"free": ""
}, {
	"title": "【日本直邮】MAISON MARGIELA 男士时尚简约米色牛皮两折短款钱包零钱包 55ui0182-516-965",
	"txt": "时尚简约",
	"price": "4935",
	"del": "4935",
	"img": "http://haitao.nos.netease.com/d1f968ab-0d15-4e27-9e92-58804ef3a979_1_1.gif",
	"minimg": "http://haitao.nosdn1.127.net/d3c18d60f0e54c32af5cf24d18be585b1419662519909i46mer1g10007.png?imageView&thumbnail=35x0&quality=85",
	"discount": "",
	"free": ""
}, {
	"title": "【日本直邮】TAGLIATORE 男士时尚竖条纹西装套装2SVS22B01-RIZ181-2",
	"txt": "时尚休闲",
	"price": "11651",
	"del": "11651",
	"img": "http://haitao.nos.netease.com/d1f968ab-0d15-4e27-9e92-58804ef3a979_1_1.gif",
	"minimg": "http://haitao.nosdn2.127.net/9ab013a727024145ae377c9a1b6286551419662432571i46mcvne10004.png?imageView&thumbnail=35x0&quality=85",
	"discount": "",
	"free": ""
}, {
	"title": "MIRACLE KILL/死亡奇迹 时尚潮牌小鸟刺绣黑色渔夫帽",
	"txt": "街头潮流 佩戴舒适",
	"price": "139",
	"del": "199",
	"img": "http://haitao.nos.netease.com/d1f968ab-0d15-4e27-9e92-58804ef3a979_1_1.gif",
	"minimg": "http://haitao.nos.netease.com/1077833fa2854dcb97502084f24f449d1419659976324i46kw8bh10001.png?imageView&thumbnail=35x0&quality=85",
	"discount": "7.0折",
	"free": ""
}, {
	"title": "【816定金预付】COACH 蔻驰 Tote系列女士单肩手提包双面敞口托特子母包",
	"txt": "子母包让你的包包更整洁",
	"price": "1118",
	"del": "3500",
	"img": "http://haitao.nos.netease.com/d1f968ab-0d15-4e27-9e92-58804ef3a979_1_1.gif",
	"minimg": "http://haitao.nos.netease.com/1077833fa2854dcb97502084f24f449d1419659976324i46kw8bh10001.png?imageView&thumbnail=35x0&quality=85",
	"discount": "3.2折",
	"free": "包邮"
}, {
	"title": "【日本直邮】EMPORIO ARMANI 安普里奥·阿玛尼 男士商务休闲简约手提单肩公文电脑包YEM823-YC043-80001",
	"txt": "时尚休闲",
	"price": "2259",
	"del": "5928",
	"img": "http://haitao.nos.netease.com/d1f968ab-0d15-4e27-9e92-58804ef3a979_1_1.gif",
	"minimg": "http://haitao.nosdn2.127.net/9ab013a727024145ae377c9a1b6286551419662432571i46mcvne10004.png?imageView&thumbnail=35x0&quality=85",
	"discount": "3.9折",
	"free": ""
}, {
	"title": "【日本直邮】GIVENCHY 纪梵希 女士真皮硬币盒钱包零钱包黑色bb6025b07y-001",
	"txt": "经典百搭",
	"price": "4925",
	"del": "4925",
	"img": "http://haitao.nos.netease.com/d1f968ab-0d15-4e27-9e92-58804ef3a979_1_1.gif",
	"minimg": "http://haitao.nosdn1.127.net/d3c18d60f0e54c32af5cf24d18be585b1419662519909i46mer1g10007.png?imageView&thumbnail=35x0&quality=85",
	"discount": "",
	"free": ""
}, {
	"title": "ESTĒE LAUDER 雅诗兰黛 晶透沁白淡斑特润霜 15毫升*1瓶装 ",
	"txt": "焕发年轻 动人光彩",
	"price": "399",
	"del": "625.5",
	"img": "http://haitao.nos.netease.com/d1f968ab-0d15-4e27-9e92-58804ef3a979_1_1.gif",
	"minimg": "http://haitao.nos.netease.com/1077833fa2854dcb97502084f24f449d1419659976324i46kw8bh10001.png?imageView&thumbnail=35x0&quality=85",
	"discount": "6.4折",
	"free": ""
}, {
	"title": "【日本直邮】ETRO 男士时尚商务藏青色聚会宴会丝绸领带 12026-3102-0200",
	"txt": "时尚商务",
	"price": "389",
	"del": "1181",
	"img": "http://haitao.nos.netease.com/d1f968ab-0d15-4e27-9e92-58804ef3a979_1_1.gif",
	"minimg": "http://haitao.nosdn2.127.net/1cc2m9est21_46_46.png?imageView&thumbnail=35x0&quality=85",
	"discount": "3.3折",
	"free": ""
}, {
	"title": "博库 马洛伊·山多尔作品：伪装成独白的爱情+烛烬+一个市民的自白",
	"txt": "马洛伊山多尔作品",
	"price": "104",
	"del": "128",
	"img": "http://haitao.nos.netease.com/d1f968ab-0d15-4e27-9e92-58804ef3a979_1_1.gif",
	"minimg": "http://haitao.nosdn2.127.net/iczukrul93.JPG?imageView&thumbnail=35x0&quality=85",
	"discount": "8.2折",
	"free": "包邮"
}, {
	"title": "【日本直邮】Chloé 蔻依 女士简约复古牛皮小猪包单肩斜挎包 p580161",
	"txt": "简约复古",
	"price": "4749",
	"del": "7752",
	"img": "http://haitao.nos.netease.com/d1f968ab-0d15-4e27-9e92-58804ef3a979_1_1.gif",
	"minimg": "http://haitao.nosdn1.127.net/d3c18d60f0e54c32af5cf24d18be585b1419662519909i46mer1g10007.png?imageView&thumbnail=35x0&quality=85",
	"discount": "6.2折",
	"free": ""
}, {
	"title": "【日本直邮】JIMMY CHOO 女士米色手拿皮包 星星图案包包 手拿零钱包",
	"txt": "女士零钱包",
	"price": "3189",
	"del": "6354",
	"img": "http://haitao.nos.netease.com/d1f968ab-0d15-4e27-9e92-58804ef3a979_1_1.gif",
	"minimg": "http://haitao.nos.netease.com/7061a236e5c94e64a41446aeb9d3d0a01419662643154i46mhe4x10008.png?imageView&thumbnail=35x0&quality=85",
	"discount": "5.1折",
	"free": ""
}, {
	"title": "【日本直邮】FURLA 芙拉 男士潮流时尚休闲纯色单肩斜挎包U517-N41-O60",
	"txt": "时尚休闲",
	"price": "1859",
	"del": "3475",
	"img": "http://haitao.nos.netease.com/d1f968ab-0d15-4e27-9e92-58804ef3a979_1_1.gif",
	"minimg": "http://haitao.nosdn2.127.net/9ab013a727024145ae377c9a1b6286551419662432571i46mcvne10004.png?imageView&thumbnail=35x0&quality=85",
	"discount": "5.4折",
	"free": ""
}, {
	"title": "【日本直邮】FINAMORE 男士休闲花色时尚领带ANVERSA3-960966-02",
	"txt": "时尚休闲",
	"price": "519",
	"del": "1235",
	"img": "http://haitao.nos.netease.com/d1f968ab-0d15-4e27-9e92-58804ef3a979_1_1.gif",
	"minimg": "http://haitao.nosdn2.127.net/9ab013a727024145ae377c9a1b6286551419662432571i46mcvne10004.png?imageView&thumbnail=35x0&quality=85",
	"discount": "4.3折",
	"free": ""
}, {
	"title": "博库 簪中录（全4册）",
	"txt": "簪中录全4册",
	"price": "97",
	"del": "128.4",
	"img": "http://haitao.nos.netease.com/d1f968ab-0d15-4e27-9e92-58804ef3a979_1_1.gif",
	"minimg": "http://haitao.nosdn2.127.net/iczukrul93.JPG?imageView&thumbnail=35x0&quality=85",
	"discount": "7.6折",
	"free": "包邮"
}, {
	"title": "【816定金预付】COACH 蔻驰 女士经典款小号单肩手提包戴妃包",
	"txt": "大容量搭配职场通勤范儿",
	"price": "1138",
	"del": "3800",
	"img": "http://haitao.nos.netease.com/d1f968ab-0d15-4e27-9e92-58804ef3a979_1_1.gif",
	"minimg": "http://haitao.nos.netease.com/1077833fa2854dcb97502084f24f449d1419659976324i46kw8bh10001.png?imageView&thumbnail=35x0&quality=85",
	"discount": "3.0折",
	"free": "包邮"
}, {
	"title": "【日本直邮】JIMMY CHOO 男士时尚潮流灰色闪光皮革星星铆钉拉链零钱包 malone-gta-gm-smx",
	"txt": "时尚潮流",
	"price": "4405",
	"del": "4405",
	"img": "http://haitao.nos.netease.com/d1f968ab-0d15-4e27-9e92-58804ef3a979_1_1.gif",
	"minimg": "http://haitao.nos.netease.com/7061a236e5c94e64a41446aeb9d3d0a01419662643154i46mhe4x10008.png?imageView&thumbnail=35x0&quality=85",
	"discount": "",
	"free": ""
}, {
	"title": "【日本直邮】STELLA McCARTNEY 斯特拉·麦卡特尼 男士运动休闲双肩背包黑色 533803-wu047-1000",
	"txt": "经典百搭",
	"price": "7608",
	"del": "7608",
	"img": "http://haitao.nos.netease.com/d1f968ab-0d15-4e27-9e92-58804ef3a979_1_1.gif",
	"minimg": "http://haitao.nos.netease.com/7061a236e5c94e64a41446aeb9d3d0a01419662643154i46mhe4x10008.png?imageView&thumbnail=35x0&quality=85",
	"discount": "",
	"free": ""
}, {
	"title": "【日本直邮】FINAMORE 男士斜条纹领带蓝色ANVERSA3-570006-02",
	"txt": "时尚休闲",
	"price": "1235",
	"del": "1235",
	"img": "http://haitao.nos.netease.com/d1f968ab-0d15-4e27-9e92-58804ef3a979_1_1.gif",
	"minimg": "http://haitao.nosdn2.127.net/9ab013a727024145ae377c9a1b6286551419662432571i46mcvne10004.png?imageView&thumbnail=35x0&quality=85",
	"discount": "",
	"free": ""
}, {
	"title": "LANCÔME兰蔻 肌底修护舒润精华液 小黑瓶 4ml*1（小安瓶）",
	"txt": "平滑舒缓，弹润去黄",
	"price": "139",
	"del": "139",
	"img": "http://haitao.nos.netease.com/d1f968ab-0d15-4e27-9e92-58804ef3a979_1_1.gif",
	"minimg": "http://haitao.nosdn1.127.net/d3c18d60f0e54c32af5cf24d18be585b1419662519909i46mer1g10007.png?imageView&thumbnail=35x0&quality=85",
	"discount": "",
	"free": ""
}, {
	"title": "【日本直邮】BALENCIAGA 巴黎世家 女士黑色手提包单肩包 526678 0otbn 1071 BB",
	"txt": "时尚百搭",
	"price": "9549",
	"del": "19074",
	"img": "http://haitao.nos.netease.com/d1f968ab-0d15-4e27-9e92-58804ef3a979_1_1.gif",
	"minimg": "http://haitao.nosdn1.127.net/d3c18d60f0e54c32af5cf24d18be585b1419662519909i46mer1g10007.png?imageView&thumbnail=35x0&quality=85",
	"discount": "5.1折",
	"free": ""
}, {
	"title": "【日本直邮】JIMMY CHOO 男士时尚潮流黑色皮革星星铆钉拉链零钱包 malone-bls-black-m",
	"txt": "时尚潮流",
	"price": "5106",
	"del": "5106",
	"img": "http://haitao.nos.netease.com/d1f968ab-0d15-4e27-9e92-58804ef3a979_1_1.gif",
	"minimg": "http://haitao.nos.netease.com/7061a236e5c94e64a41446aeb9d3d0a01419662643154i46mhe4x10008.png?imageView&thumbnail=35x0&quality=85",
	"discount": "",
	"free": ""
}, {
	"title": "【日本直邮】LARDINI 男士休闲纯棉西服套装EE041AV-50528-0096",
	"txt": "时尚休闲",
	"price": "8667",
	"del": "8667",
	"img": "http://haitao.nos.netease.com/d1f968ab-0d15-4e27-9e92-58804ef3a979_1_1.gif",
	"minimg": "http://haitao.nosdn2.127.net/9ab013a727024145ae377c9a1b6286551419662432571i46mcvne10004.png?imageView&thumbnail=35x0&quality=85",
	"discount": "",
	"free": ""
}, {
	"title": "【日本直邮】J&M Davidson  新款 男士皮革编织皮带",
	"txt": "舒适时尚 成熟稳重",
	"price": "1409",
	"del": "2599",
	"img": "http://haitao.nos.netease.com/d1f968ab-0d15-4e27-9e92-58804ef3a979_1_1.gif",
	"minimg": "http://haitao.nos.netease.com/7061a236e5c94e64a41446aeb9d3d0a01419662643154i46mhe4x10008.png?imageView&thumbnail=35x0&quality=85",
	"discount": "5.5折",
	"free": ""
}, {
	"title": "博库 读者原创版文集 共4册",
	"txt": "读者原创版文集 共4册",
	"price": "90",
	"del": "119.2",
	"img": "http://haitao.nos.netease.com/d1f968ab-0d15-4e27-9e92-58804ef3a979_1_1.gif",
	"minimg": "http://haitao.nosdn2.127.net/iczukrul93.JPG?imageView&thumbnail=35x0&quality=85",
	"discount": "7.6折",
	"free": "包邮"
}, {
	"title": "【816定金预付】COACH 蔻驰 女士百搭单肩斜挎小包",
	"txt": "精致小巧圆饼包上身秒减龄",
	"price": "899",
	"del": "2999",
	"img": "http://haitao.nos.netease.com/d1f968ab-0d15-4e27-9e92-58804ef3a979_1_1.gif",
	"minimg": "http://haitao.nos.netease.com/1077833fa2854dcb97502084f24f449d1419659976324i46kw8bh10001.png?imageView&thumbnail=35x0&quality=85",
	"discount": "3.0折",
	"free": "包邮"
}, {
	"title": "【日本直邮】BALENCIAGA 巴黎世家 女士时尚潮流精美休闲鞋运动鞋 524039 w09o6 9063",
	"txt": "时尚潮流",
	"price": "6649",
	"del": "10644",
	"img": "http://haitao.nos.netease.com/d1f968ab-0d15-4e27-9e92-58804ef3a979_1_1.gif",
	"minimg": "http://haitao.nosdn1.127.net/d3c18d60f0e54c32af5cf24d18be585b1419662519909i46mer1g10007.png?imageView&thumbnail=35x0&quality=85",
	"discount": "6.3折",
	"free": ""
}, {
	"title": "博库 为你打开时间的门+为你打开时间的门(完结篇)（共2册）",
	"txt": "为你打开时间的门你打",
	"price": "56",
	"del": "65.6",
	"img": "http://haitao.nos.netease.com/d1f968ab-0d15-4e27-9e92-58804ef3a979_1_1.gif",
	"minimg": "http://haitao.nosdn2.127.net/iczukrul93.JPG?imageView&thumbnail=35x0&quality=85",
	"discount": "8.6折",
	"free": "包邮"
}, {
	"title": "【法国直邮包邮】Avène 雅漾 三重修护滋养霜 400毫升 活泉保湿",
	"txt": "活泉温养，愈合损伤",
	"price": "169",
	"del": "390",
	"img": "http://haitao.nos.netease.com/d1f968ab-0d15-4e27-9e92-58804ef3a979_1_1.gif",
	"minimg": "http://haitao.nosdn1.127.net/d3c18d60f0e54c32af5cf24d18be585b1419662519909i46mer1g10007.png?imageView&thumbnail=35x0&quality=85",
	"discount": "4.4折",
	"free": "包邮"
}, {
	"title": "Alpha Industries x NASA联名款AL178501男士短袖T恤19年夏季新款",
	"txt": "阿尔法男士短袖T恤",
	"price": "409",
	"del": "698",
	"img": "http://haitao.nos.netease.com/d1f968ab-0d15-4e27-9e92-58804ef3a979_1_1.gif",
	"minimg": "http://haitao.nos.netease.com/1077833fa2854dcb97502084f24f449d1419659976324i46kw8bh10001.png?imageView&thumbnail=35x0&quality=85",
	"discount": "5.9折",
	"free": "包邮"
}, {
	"title": "halsanr画尚北欧换鞋凳进门简约现代实木门口可坐鞋架鞋柜收纳储物凳子穿鞋凳",
	"txt": "品质家居 北欧简约风",
	"price": "219",
	"del": "440",
	"img": "http://haitao.nos.netease.com/d1f968ab-0d15-4e27-9e92-58804ef3a979_1_1.gif",
	"minimg": "http://haitao.nosdn2.127.net/iczukrul93.JPG?imageView&thumbnail=35x0&quality=85",
	"discount": "5.0折",
	"free": ""
}, {
	"title": "Converse匡威童装女童渐变七彩连帽开衫卫衣插肩蝙蝠袖",
	"txt": "Converse匡威",
	"price": "339",
	"del": "339",
	"img": "http://haitao.nos.netease.com/d1f968ab-0d15-4e27-9e92-58804ef3a979_1_1.gif",
	"minimg": "http://haitao.nos.netease.com/1077833fa2854dcb97502084f24f449d1419659976324i46kw8bh10001.png?imageView&thumbnail=35x0&quality=85",
	"discount": "包邮",
	"free": ""
}, {
	"title": "博库 沙丘系列 共5册",
	"txt": "沙丘系列 共5册",
	"price": "223",
	"del": "322.9",
	"img": "http://haitao.nos.netease.com/d1f968ab-0d15-4e27-9e92-58804ef3a979_1_1.gif",
	"minimg": "http://haitao.nosdn2.127.net/iczukrul93.JPG?imageView&thumbnail=35x0&quality=85",
	"discount": "7.0折",
	"free": "包邮"
}, {
	"title": "【法国直邮包邮】Avène 雅漾 祛油清痘乳 40毫升",
	"txt": "平衡水油 痘肌适用",
	"price": "130",
	"del": "199",
	"img": "http://haitao.nos.netease.com/d1f968ab-0d15-4e27-9e92-58804ef3a979_1_1.gif",
	"minimg": "http://haitao.nosdn1.127.net/d3c18d60f0e54c32af5cf24d18be585b1419662519909i46mer1g10007.png?imageView&thumbnail=35x0&quality=85",
	"discount": "6.6折",
	"free": "包邮"
}, {
	"title": "Alpha Industries阿尔法AL156101男士休闲拉链夹克外套19年新款",
	"txt": "男士休闲拉链夹克外套",
	"price": "1269",
	"del": "2520",
	"img": "http://haitao.nos.netease.com/d1f968ab-0d15-4e27-9e92-58804ef3a979_1_1.gif",
	"minimg": "http://haitao.nos.netease.com/1077833fa2854dcb97502084f24f449d1419659976324i46kw8bh10001.png?imageView&thumbnail=35x0&quality=85",
	"discount": "5.1折",
	"free": "包邮"
}, {
	"title": "MOSCHINO莫斯奇诺19春夏新款猪年限定男女同款猪小弟刺绣短袖T恤D1A0779",
	"txt": "MOSCHINO莫斯奇诺",
	"price": "1889",
	"del": "5980",
	"img": "http://haitao.nos.netease.com/d1f968ab-0d15-4e27-9e92-58804ef3a979_1_1.gif",
	"minimg": "http://haitao.nosdn2.127.net/9ab013a727024145ae377c9a1b6286551419662432571i46mcvne10004.png?imageView&thumbnail=35x0&quality=85",
	"discount": "3.2折",
	"free": ""
}, {
	"title": "【2瓶】原装进口ACQUA ALLE ROSE艾可玫玫瑰爽肤水300ml瓶 意大利古老玫瑰滋润纯露 补水保湿面膜水",
	"txt": "艾可玫玫瑰爽肤水",
	"price": "59",
	"del": "103",
	"img": "http://haitao.nos.netease.com/d1f968ab-0d15-4e27-9e92-58804ef3a979_1_1.gif",
	"minimg": "http://haitao.nosdn2.127.net/9ab013a727024145ae377c9a1b6286551419662432571i46mcvne10004.png?imageView&thumbnail=35x0&quality=85",
	"discount": "5.8折",
	"free": "包邮"
}, {
	"title": "博库 哈佛牛津学生爱玩的游戏系列 共四册 8-14岁",
	"txt": "思维游戏 图文结合 数独",
	"price": "38",
	"del": "51.2",
	"img": "http://haitao.nos.netease.com/d1f968ab-0d15-4e27-9e92-58804ef3a979_1_1.gif",
	"minimg": "http://haitao.nosdn2.127.net/iczukrul93.JPG?imageView&thumbnail=35x0&quality=85",
	"discount": "7.5折",
	"free": ""
}, {
	"title": "GUUKA撞色拼接卫衣2019新款女嘻哈情侣纯棉印花连帽运动卫衣宽松\n",
	"txt": "印花连帽运动撞色拼接",
	"price": "349.2",
	"del": "518",
	"img": "http://haitao.nos.netease.com/d1f968ab-0d15-4e27-9e92-58804ef3a979_1_1.gif",
	"minimg": "http://haitao.nosdn2.127.net/iczukrul93.JPG?imageView&thumbnail=35x0&quality=85",
	"discount": "6.8折",
	"free": ""
}, {
	"title": "【法国直邮包邮】Avène 雅漾 舒活保湿面膜 50毫升",
	"txt": "修护受损肌肤",
	"price": "129",
	"del": "245",
	"img": "http://haitao.nos.netease.com/d1f968ab-0d15-4e27-9e92-58804ef3a979_1_1.gif",
	"minimg": "http://haitao.nosdn1.127.net/d3c18d60f0e54c32af5cf24d18be585b1419662519909i46mer1g10007.png?imageView&thumbnail=35x0&quality=85",
	"discount": "5.3折",
	"free": "包邮"
}, {
	"title": "博库 掌舵1+掌舵2 共2册",
	"txt": "掌舵掌舵",
	"price": "71",
	"del": "79.6",
	"img": "http://haitao.nos.netease.com/d1f968ab-0d15-4e27-9e92-58804ef3a979_1_1.gif",
	"minimg": "http://haitao.nosdn2.127.net/iczukrul93.JPG?imageView&thumbnail=35x0&quality=85",
	"discount": "9.0折",
	"free": "包邮"
}, {
	"title": "【法国直邮包邮】Avène 雅漾 滋润冷霜 100毫升 消敏感舒缓修护保湿滋润修护",
	"txt": "舒缓修护，敏感肌福音",
	"price": "145",
	"del": "150",
	"img": "http://haitao.nos.netease.com/d1f968ab-0d15-4e27-9e92-58804ef3a979_1_1.gif",
	"minimg": "http://haitao.nosdn1.127.net/d3c18d60f0e54c32af5cf24d18be585b1419662519909i46mer1g10007.png?imageView&thumbnail=35x0&quality=85",
	"discount": "9.7折",
	"free": "包邮"
}, {
	"title": "博库 周易&易经 共2册",
	"txt": "周易 易经",
	"price": "30",
	"del": "32.6",
	"img": "http://haitao.nos.netease.com/d1f968ab-0d15-4e27-9e92-58804ef3a979_1_1.gif",
	"minimg": "http://haitao.nosdn2.127.net/iczukrul93.JPG?imageView&thumbnail=35x0&quality=85",
	"discount": "9.3折",
	"free": "包邮"
}, {
	"title": "博库 我要了解自己：青少年情绪管理手册（共2册）",
	"txt": "我要了解自己青少年情绪",
	"price": "38",
	"del": "39.6",
	"img": "http://haitao.nos.netease.com/d1f968ab-0d15-4e27-9e92-58804ef3a979_1_1.gif",
	"minimg": "http://haitao.nosdn2.127.net/iczukrul93.JPG?imageView&thumbnail=35x0&quality=85",
	"discount": "9.6折",
	"free": "包邮"
}, {
	"title": "博库 莫妮卡·菲特国际大奖短篇小说：收集思想的人+擦亮路牌的人+",
	"txt": "莫妮卡菲特国际大奖短篇",
	"price": "60",
	"del": "63.2",
	"img": "http://haitao.nos.netease.com/d1f968ab-0d15-4e27-9e92-58804ef3a979_1_1.gif",
	"minimg": "http://haitao.nosdn2.127.net/iczukrul93.JPG?imageView&thumbnail=35x0&quality=85",
	"discount": "9.5折",
	"free": "包邮"
}, {
	"title": "博库 巨虫公园 共3册",
	"txt": "巨虫公园 共3册",
	"price": "62",
	"del": "78",
	"img": "http://haitao.nos.netease.com/d1f968ab-0d15-4e27-9e92-58804ef3a979_1_1.gif",
	"minimg": "http://haitao.nosdn2.127.net/iczukrul93.JPG?imageView&thumbnail=35x0&quality=85",
	"discount": "8.0折",
	"free": "包邮"
}, {
	"title": "博库 微表情(如何识别他人脸面真假黄金修订版)+微反应(小动作背",
	"txt": "微表情 如何识别他人脸面",
	"price": "68",
	"del": "75.8",
	"img": "http://haitao.nos.netease.com/d1f968ab-0d15-4e27-9e92-58804ef3a979_1_1.gif",
	"minimg": "http://haitao.nosdn2.127.net/iczukrul93.JPG?imageView&thumbnail=35x0&quality=85",
	"discount": "9.0折",
	"free": "包邮"
}, {
	"title": "博库 生死场(萧红小说精选集)&呼兰河传 共2册",
	"txt": "生死场萧红小说精选集",
	"price": "62",
	"del": "78",
	"img": "http://haitao.nos.netease.com/d1f968ab-0d15-4e27-9e92-58804ef3a979_1_1.gif",
	"minimg": "http://haitao.nosdn2.127.net/iczukrul93.JPG?imageView&thumbnail=35x0&quality=85",
	"discount": "8.0折",
	"free": "包邮"
}, {
	"title": "【补充氨基酸 腿脚更灵活】BLACKMORES 澳佳宝 维骨力硫酸葡萄糖胺 180片/瓶",
	"txt": "补充氨基酸 腿脚更灵活",
	"price": "159",
	"del": "219",
	"img": "http://haitao.nos.netease.com/d1f968ab-0d15-4e27-9e92-58804ef3a979_1_1.gif",
	"minimg": "http://haitao.nosdn2.127.net/8b99e5ba0d42459aa6d982698dd7d1d51419662720539i46mj1ui10010.png?imageView&thumbnail=35x0&quality=85",
	"discount": "7.3折",
	"free": "包邮"
}, {
	"title": "Skechers斯凯奇男鞋新款时尚运动鞋 轻质舒适低帮休闲鞋 51908\n",
	"txt": "简约休闲舒适回弹",
	"price": "369",
	"del": "599",
	"img": "http://haitao.nos.netease.com/d1f968ab-0d15-4e27-9e92-58804ef3a979_1_1.gif",
	"minimg": "http://haitao.nos.netease.com/1077833fa2854dcb97502084f24f449d1419659976324i46kw8bh10001.png?imageView&thumbnail=35x0&quality=85",
	"discount": "6.2折",
	"free": ""
}, {
	"title": "【日本直邮】Thom Browne 男士时尚简约黑色皮革卡包零钱包 maw092a-00198-001",
	"txt": "时尚简约",
	"price": "2459",
	"del": "5106",
	"img": "http://haitao.nos.netease.com/d1f968ab-0d15-4e27-9e92-58804ef3a979_1_1.gif",
	"minimg": "http://haitao.nos.netease.com/1077833fa2854dcb97502084f24f449d1419659976324i46kw8bh10001.png?imageView&thumbnail=35x0&quality=85",
	"discount": "4.9折",
	"free": ""
}, {
	"title": "Jurlique茱莉蔻 玫瑰身体乳滋润型 300ml 均匀肤色 焕发光彩",
	"txt": "丝般柔嫩，自然透亮",
	"price": "169",
	"del": "375",
	"img": "http://haitao.nos.netease.com/d1f968ab-0d15-4e27-9e92-58804ef3a979_1_1.gif",
	"minimg": "http://haitao.nosdn2.127.net/8b99e5ba0d42459aa6d982698dd7d1d51419662720539i46mj1ui10010.png?imageView&thumbnail=35x0&quality=85",
	"discount": "4.6折",
	"free": ""
}, {
	"title": "【日本直邮】ETRO 男士时尚商务藏青色聚会宴会丝绸领带 12026-5006-0200",
	"txt": "时尚商务",
	"price": "489",
	"del": "1181",
	"img": "http://haitao.nos.netease.com/d1f968ab-0d15-4e27-9e92-58804ef3a979_1_1.gif",
	"minimg": "http://haitao.nosdn2.127.net/1cc2m9est21_46_46.png?imageView&thumbnail=35x0&quality=85",
	"discount": "4.2折",
	"free": ""
}, {
	"title": "CLARINS娇韵诗 SOS急救蓝膜 75ml （滋润舒缓）密集保湿 注入活力 令肌肤更丰盈 柔嫩细致",
	"txt": "密集保湿，注入活力",
	"price": "229",
	"del": "399",
	"img": "http://haitao.nos.netease.com/d1f968ab-0d15-4e27-9e92-58804ef3a979_1_1.gif",
	"minimg": "http://haitao.nosdn1.127.net/d3c18d60f0e54c32af5cf24d18be585b1419662519909i46mer1g10007.png?imageView&thumbnail=35x0&quality=85",
	"discount": "5.8折",
	"free": ""
}, {
	"title": "博库 想开一个店（1-3 共3册）",
	"txt": "想开一个店",
	"price": "113",
	"del": "157.6",
	"img": "http://haitao.nos.netease.com/d1f968ab-0d15-4e27-9e92-58804ef3a979_1_1.gif",
	"minimg": "http://haitao.nosdn2.127.net/iczukrul93.JPG?imageView&thumbnail=35x0&quality=85",
	"discount": "7.2折",
	"free": "包邮"
}, {
	"title": "【日本直邮】EMPORIO ARMANI 安普里奥·阿玛尼 男士时尚简约潮流长款两折钱包Y4R060-YG91J-81072",
	"txt": "时尚休闲",
	"price": "889",
	"del": "1840",
	"img": "http://haitao.nos.netease.com/d1f968ab-0d15-4e27-9e92-58804ef3a979_1_1.gif",
	"minimg": "http://haitao.nosdn2.127.net/9ab013a727024145ae377c9a1b6286551419662432571i46mcvne10004.png?imageView&thumbnail=35x0&quality=85",
	"discount": "4.9折",
	"free": ""
}, {
	"title": "Jurlique茱莉蔻 薰衣草洗发水 300ml  檀香木 温和清洁 滋养保湿 舒缓头皮",
	"txt": "温和清洁，滋养保湿",
	"price": "110",
	"del": "198",
	"img": "http://haitao.nos.netease.com/d1f968ab-0d15-4e27-9e92-58804ef3a979_1_1.gif",
	"minimg": "http://haitao.nosdn2.127.net/8b99e5ba0d42459aa6d982698dd7d1d51419662720539i46mj1ui10010.png?imageView&thumbnail=35x0&quality=85",
	"discount": "5.6折",
	"free": ""
}, {
	"title": "【日本直邮】STELLA McCARTNEY 斯特拉·麦卡特尼女士简约羊皮子母包大容量托特包",
	"txt": "简约大容量",
	"price": "4079",
	"del": "7592",
	"img": "http://haitao.nos.netease.com/d1f968ab-0d15-4e27-9e92-58804ef3a979_1_1.gif",
	"minimg": "http://haitao.nos.netease.com/7061a236e5c94e64a41446aeb9d3d0a01419662643154i46mhe4x10008.png?imageView&thumbnail=35x0&quality=85",
	"discount": "5.4折",
	"free": ""
}, {
	"title": "CLARINS娇韵诗 抗纹乳霜 200ml Minimizer 滋养平滑肌肤 淡化身体纹 孕期不长纹",
	"txt": "减轻肌肤紧绷感令肌肤滋润",
	"price": "359",
	"del": "510",
	"img": "http://haitao.nos.netease.com/d1f968ab-0d15-4e27-9e92-58804ef3a979_1_1.gif",
	"minimg": "http://haitao.nosdn1.127.net/d3c18d60f0e54c32af5cf24d18be585b1419662519909i46mer1g10007.png?imageView&thumbnail=35x0&quality=85",
	"discount": "7.1折",
	"free": ""
}, {
	"title": "【张一山同款】KennethCole手表男士皮带腕表新款KC镂空酒桶型防水自动机械表",
	"txt": "型酷利器时髦有品",
	"price": "1679",
	"del": "1880",
	"img": "http://haitao.nos.netease.com/d1f968ab-0d15-4e27-9e92-58804ef3a979_1_1.gif",
	"minimg": "http://haitao.nos.netease.com/1077833fa2854dcb97502084f24f449d1419659976324i46kw8bh10001.png?imageView&thumbnail=35x0&quality=85",
	"discount": "9.0折",
	"free": "包邮"
}, {
	"title": "【日本直邮】MAISON MARGIELA 男士腰包尼龙包白色55wb0010-253-100",
	"txt": "经典百搭",
	"price": "3399",
	"del": "5086",
	"img": "http://haitao.nos.netease.com/d1f968ab-0d15-4e27-9e92-58804ef3a979_1_1.gif",
	"minimg": "http://haitao.nosdn1.127.net/d3c18d60f0e54c32af5cf24d18be585b1419662519909i46mer1g10007.png?imageView&thumbnail=35x0&quality=85",
	"discount": "6.7折",
	"free": ""
}, {
	"title": "耐克NIKE LUNARSOLO 男子缓震透气跑步鞋 运动休闲男鞋 AA4079",
	"txt": "轻质缓震，舒适透气",
	"price": "379",
	"del": "869",
	"img": "http://haitao.nos.netease.com/d1f968ab-0d15-4e27-9e92-58804ef3a979_1_1.gif",
	"minimg": "http://haitao.nos.netease.com/1077833fa2854dcb97502084f24f449d1419659976324i46kw8bh10001.png?imageView&thumbnail=35x0&quality=85",
	"discount": "4.4折",
	"free": ""
}, {
	"title": "精装完整版44册 四大名著 国外名著 课外阅读 自传体小说 初中高中青少版世界文学小说名著课外书籍",
	"txt": "精装完整版44册 四大名著",
	"price": "399",
	"del": "512",
	"img": "http://haitao.nos.netease.com/d1f968ab-0d15-4e27-9e92-58804ef3a979_1_1.gif",
	"minimg": "http://haitao.nosdn2.127.net/iczukrul93.JPG?imageView&thumbnail=35x0&quality=85",
	"discount": "7.8折",
	"free": ""
}, {
	"title": "【张韶涵同款】CLARINS娇韵诗 双萃赋活修复精华 30ml 修护保湿 焕活细胞年轻力",
	"txt": "天然植萃，唤醒细胞原生力",
	"price": "480",
	"del": "780",
	"img": "http://pop.nosdn.127.net/2584cb8e-a12c-4fd6-b4d0-6be17c904700?imageView&thumbnail=524x0&quality=85",
	"minimg": "http://haitao.nosdn1.127.net/d3c18d60f0e54c32af5cf24d18be585b1419662519909i46mer1g10007.png?imageView&thumbnail=35x0&quality=85",
	"discount": "6.2折",
	"free": ""
}, {
	"title": "Danielwellington丹尼尔惠灵顿dw手镯手表配饰饰品男女手镯dw手镯陶瓷白",
	"txt": "优雅配色，重塑经典",
	"price": "790",
	"del": "790",
	"img": "http://pop.nosdn.127.net/0f58a1e5-8461-4f01-b4f7-9bcdb9375e90?imageView&thumbnail=524x0&quality=85",
	"minimg": "http://haitao.nosdn2.127.net/b2e92feaafc649038428beebc778040b1419663645020i46n2v6j10027.png?imageView&thumbnail=35x0&quality=85",
	"discount": "包邮",
	"free": ""
}, {
	"title": "【日本直邮】Daniel&Bob 简约百搭男士尼龙腰包dab-p168",
	"txt": "简约百搭",
	"price": "2129",
	"del": "3158",
	"img": "http://pop.nosdn.127.net/171e162c-470c-4ff5-ba8f-10ed05e5ed38.jpg?imageView&thumbnail=524x0&quality=85",
	"minimg": "http://haitao.nosdn2.127.net/9ab013a727024145ae377c9a1b6286551419662432571i46mcvne10004.png?imageView&thumbnail=35x0&quality=85",
	"discount": "6.8折",
	"free": ""
}, {
	"title": "【日本直邮】COACH 蔻驰 女士轻便环保黑色皮革拼接麦秆草编包单肩包斜挎包 F73070 IMOU0",
	"txt": "时尚轻便",
	"price": "1099",
	"del": "1579",
	"img": "http://pop.nosdn.127.net/56dbb830-65c6-460d-8c30-e29102270d7e?imageView&thumbnail=524x0&quality=85",
	"minimg": "http://haitao.nos.netease.com/1077833fa2854dcb97502084f24f449d1419659976324i46kw8bh10001.png?imageView&thumbnail=35x0&quality=85",
	"discount": "7.0折",
	"free": ""
}, {
	"title": "【日本直邮】DUVETICA 女士通勤户外高腰羽绒服ACE-1087",
	"txt": "时尚休闲",
	"price": "5039",
	"del": "9058",
	"img": "http://pop.nosdn.127.net/6a7570fb-e466-406d-a672-497c8b6d3565?imageView&thumbnail=524x0&quality=85",
	"minimg": "http://haitao.nosdn2.127.net/9ab013a727024145ae377c9a1b6286551419662432571i46mcvne10004.png?imageView&thumbnail=35x0&quality=85",
	"discount": "5.6折",
	"free": ""
}, {
	"title": "CLARINS娇韵诗温和泡沫洁面霜 125ml 温和不刺激 令肌肤柔软平滑 充满光泽 水油得到平衡",
	"txt": "深层清洁，修护肌肤",
	"price": "199",
	"del": "250",
	"img": "http://pop.nosdn.127.net/1f7c99c7-2456-4c6d-8c60-2c7a8403fc22?imageView&thumbnail=524x0&quality=85",
	"minimg": "http://haitao.nosdn1.127.net/d3c18d60f0e54c32af5cf24d18be585b1419662519909i46mer1g10007.png?imageView&thumbnail=35x0&quality=85",
	"discount": "8.0折",
	"free": ""
}, {
	"title": "博库 文明之光(1-4) 共4册",
	"txt": "文明之光共4",
	"price": "177",
	"del": "246",
	"img": "http://pop.nosdn.127.net/b619c668-bdc0-49cf-9af3-45731e8f5557?imageView&thumbnail=524x0&quality=85",
	"minimg": "http://haitao.nosdn2.127.net/iczukrul93.JPG?imageView&thumbnail=35x0&quality=85",
	"discount": "7.2折",
	"free": "包邮"
}, {
	"title": "【日本直邮】HUNTING WORLD 经典实用长款钱包 579-2-233",
	"txt": "经典实用",
	"price": "2399",
	"del": "3603",
	"img": "http://pop.nosdn.127.net/9a03138d-58a0-4f73-861a-bcb78a53211f.jpg?imageView&thumbnail=524x0&quality=85",
	"minimg": "http://haitao.nos.netease.com/1077833fa2854dcb97502084f24f449d1419659976324i46kw8bh10001.png?imageView&thumbnail=35x0&quality=85",
	"discount": "6.7折",
	"free": ""
}, {
	"title": "【大促特价】CASIO 卡西欧BABY-G 双表盘世界时间MSG-400G-7ADR",
	"txt": "至臻之选",
	"price": "1591",
	"del": "1762",
	"img": "http://pop.nosdn.127.net/52248538-3e5c-448f-98c7-14d30bdba082?imageView&thumbnail=524x0&quality=85",
	"minimg": "http://haitao.nosdn2.127.net/1cc2m9est21_46_46.png?imageView&thumbnail=35x0&quality=85",
	"discount": "9.1折",
	"free": ""
}, {
	"title": "bebe2019早秋新品女士格纹褶裥不对称连衣裙 320201",
	"txt": "不对称设计半身裙",
	"price": "1398",
	"del": "1398",
	"img": "http://pop.nosdn.127.net/723213aa-857b-4839-91d8-34a4ddbb76db?imageView&thumbnail=524x0&quality=85",
	"minimg": "http://haitao.nos.netease.com/1077833fa2854dcb97502084f24f449d1419659976324i46kw8bh10001.png?imageView&thumbnail=35x0&quality=85",
	"discount": "包邮",
	"free": ""
}, {
	"title": "CLARINS娇韵诗 活肤舒缓泡沫洁面霜 125ml 温和清洁 舒缓肌肤",
	"txt": "温和清洁，舒缓肌肤",
	"price": "210",
	"del": "280",
	"img": "http://pop.nosdn.127.net/e4a27e04-6221-4afb-a17f-512f5e55c352?imageView&thumbnail=524x0&quality=85",
	"minimg": "http://haitao.nosdn1.127.net/d3c18d60f0e54c32af5cf24d18be585b1419662519909i46mer1g10007.png?imageView&thumbnail=35x0&quality=85",
	"discount": "7.5折",
	"free": ""
}, {
	"title": "博库 数学就是这么有趣(修炼篇+升级篇)（共2册）",
	"txt": "数学就是这么有趣修炼篇",
	"price": "38",
	"del": "40",
	"img": "http://pop.nosdn.127.net/98b31ccf-d480-422c-90df-7fd514f95eb5?imageView&thumbnail=524x0&quality=85",
	"minimg": "http://haitao.nosdn2.127.net/iczukrul93.JPG?imageView&thumbnail=35x0&quality=85",
	"discount": "9.5折",
	"free": "包邮"
}, {
	"title": "【日本直邮】HUNTING WORLD 经典实用钥匙包男女  500-13a",
	"txt": "经典实用",
	"price": "1199",
	"del": "1801",
	"img": "http://pop.nosdn.127.net/913f1c86-db9d-4f47-92c3-aa3563d5fada.jpg?imageView&thumbnail=524x0&quality=85",
	"minimg": "http://haitao.nos.netease.com/1077833fa2854dcb97502084f24f449d1419659976324i46kw8bh10001.png?imageView&thumbnail=35x0&quality=85",
	"discount": "6.7折",
	"free": ""
}, {
	"title": "【日本直邮】San Carlino 经典百搭男士胸针花朵黑色系cineralia-mono-no",
	"txt": "经典百搭",
	"price": "239",
	"del": "343",
	"img": "http://pop.nosdn.127.net/d3c43db7-cda4-4a56-a20e-5d4fb786d190.jpg?imageView&thumbnail=524x0&quality=85",
	"minimg": "http://haitao.nosdn2.127.net/9ab013a727024145ae377c9a1b6286551419662432571i46mcvne10004.png?imageView&thumbnail=35x0&quality=85",
	"discount": "7.0折",
	"free": ""
}, {
	"title": "西川NISHIKAWA 日本制毛巾2条装 纯棉洗脸巾 吸水全棉家用成人儿童毛巾 柔软面巾 颜色备注 ",
	"txt": "皮肤科医生都推荐的毛巾",
	"price": "439",
	"del": "596",
	"img": "http://pop.nosdn.127.net/dbcec806-386c-4351-983d-ac40144ae791?imageView&thumbnail=524x0&quality=85",
	"minimg": "http://haitao.nosdn2.127.net/1cc2m9est21_46_46.png?imageView&thumbnail=35x0&quality=85",
	"discount": "7.4折",
	"free": "包邮"
}, {
	"title": "CLARINS娇韵诗 沁润清凉啫喱（混/干） 50ml 持久补水 轻盈不黏腻",
	"txt": "4层浸透，源源补水",
	"price": "369",
	"del": "498",
	"img": "http://pop.nosdn.127.net/f5ea5bc8-3ae1-4cb2-97ab-e83c87e6f6ff?imageView&thumbnail=524x0&quality=85",
	"minimg": "http://haitao.nosdn1.127.net/d3c18d60f0e54c32af5cf24d18be585b1419662519909i46mer1g10007.png?imageView&thumbnail=35x0&quality=85",
	"discount": "7.5折",
	"free": ""
}, {
	"title": "中信出版社 火车之书",
	"txt": "隐藏游戏锻炼专注力",
	"price": "40.8",
	"del": "68",
	"img": "http://pop.nosdn.127.net/1f6282d9-c541-420e-be14-b22eaf8aa590?imageView&thumbnail=524x0&quality=85",
	"minimg": "http://haitao.nosdn2.127.net/iczukrul93.JPG?imageView&thumbnail=35x0&quality=85",
	"discount": "6.0折",
	"free": ""
}, {
	"title": "【日本直邮】HUNTING WORLD 经典百搭长款钱包黑色男 579-1-233",
	"txt": "经典百搭",
	"price": "2659",
	"del": "4027",
	"img": "http://pop.nosdn.127.net/f93ce138-529f-419a-9277-608c7cd5e19e.jpg?imageView&thumbnail=524x0&quality=85",
	"minimg": "http://haitao.nos.netease.com/1077833fa2854dcb97502084f24f449d1419659976324i46kw8bh10001.png?imageView&thumbnail=35x0&quality=85",
	"discount": "6.7折",
	"free": ""
}, {
	"title": "Linden Leaves薰衣草沐浴液200毫升",
	"txt": "舒缓肌肤 滋润保湿",
	"price": "199",
	"del": "199",
	"img": "http://pop.nosdn.127.net/8bb2a6d3-a0c5-4e51-81a4-34cfa4c6de9c?imageView&thumbnail=524x0&quality=85",
	"minimg": "http://haitao.nosdn2.127.net/7489e52daa45487c959de15a903495fb1419662677354i46mi4ix10009.png?imageView&thumbnail=35x0&quality=85",
	"discount": "包邮",
	"free": ""
}, {
	"title": "Jurlique茱莉蔻 按摩油 100ml 玫瑰 柠檬  质地轻盈 舒缓毛孔 帮助睡眠 白昼滋润\n",
	"txt": "质地轻盈 舒缓毛孔 ",
	"price": "129",
	"del": "259",
	"img": "http://pop.nosdn.127.net/f0e64f01-4970-4a3a-adc2-278ea79ec99b?imageView&thumbnail=524x0&quality=85",
	"minimg": "http://haitao.nosdn2.127.net/8b99e5ba0d42459aa6d982698dd7d1d51419662720539i46mj1ui10010.png?imageView&thumbnail=35x0&quality=85",
	"discount": "5.0折",
	"free": ""
}, {
	"title": "SKIN PHYSICS菲泽斯 龙血清滢净润洁面乳 150ml 氨基酸 深层清洁 控油",
	"txt": "温和洁面 不含皂质",
	"price": "115",
	"del": "189",
	"img": "http://pop.nosdn.127.net/97769aa1-edff-4f5c-a0f1-11ad49bfa44d?imageView&thumbnail=524x0&quality=85",
	"minimg": "http://haitao.nosdn2.127.net/8b99e5ba0d42459aa6d982698dd7d1d51419662720539i46mj1ui10010.png?imageView&thumbnail=35x0&quality=85",
	"discount": "6.1折",
	"free": ""
}, {
	"title": "【日本直邮】San Carlino 经典百搭男士胸针花朵蓝色系myosotis-arg-blu",
	"txt": "经典百搭",
	"price": "289",
	"del": "389",
	"img": "http://pop.nosdn.127.net/f0660881-38a9-43b4-85ac-d3add4c45f4c.jpg?imageView&thumbnail=524x0&quality=85",
	"minimg": "http://haitao.nosdn2.127.net/9ab013a727024145ae377c9a1b6286551419662432571i46mcvne10004.png?imageView&thumbnail=35x0&quality=85",
	"discount": "7.5折",
	"free": ""
}, {
	"title": "【日本直邮】FURLA 芙拉 经典百搭女士真皮2折钱包零钱包黑色bpr85-b30-o60",
	"txt": "经典百搭",
	"price": "819",
	"del": "1601",
	"img": "http://pop.nosdn.127.net/31d6dad4-1fa9-4835-80bc-4ba9b5a6771b.jpg?imageView&thumbnail=524x0&quality=85",
	"minimg": "http://haitao.nosdn2.127.net/9ab013a727024145ae377c9a1b6286551419662432571i46mcvne10004.png?imageView&thumbnail=35x0&quality=85",
	"discount": "5.2折",
	"free": ""
}, {
	"title": "博库 请不要随便欺负我&请不要随便摸我 共2册",
	"txt": "请不要随便欺负我请不要",
	"price": "61",
	"del": "74.8",
	"img": "http://pop.nosdn.127.net/4597c12f-f72b-482d-94cd-47950f89df1f?imageView&thumbnail=524x0&quality=85",
	"minimg": "http://haitao.nosdn2.127.net/iczukrul93.JPG?imageView&thumbnail=35x0&quality=85",
	"discount": "8.2折",
	"free": "包邮"
}, {
	"title": "Danielwellington丹尼尔惠灵顿dw手镯手表配饰饰品男女手镯dw手镯晨雾灰",
	"txt": "优雅配色重塑经典",
	"price": "790",
	"del": "790",
	"img": "http://pop.nosdn.127.net/d796610a-fff5-4af1-a98e-e85cfbda49e1?imageView&thumbnail=524x0&quality=85",
	"minimg": "http://haitao.nosdn2.127.net/b2e92feaafc649038428beebc778040b1419663645020i46n2v6j10027.png?imageView&thumbnail=35x0&quality=85",
	"discount": "包邮",
	"free": ""
}, {
	"title": "【不死鸟水精华】CLARINS娇韵诗 沁润奇肌保湿精华液 30ml/50ml 长效锁水 深层保湿",
	"txt": "蓄水锁水，深层保湿",
	"price": "388",
	"del": "530",
	"img": "http://pop.nosdn.127.net/e2707757-706e-4ee5-9a08-7c9c1a468548?imageView&thumbnail=524x0&quality=85",
	"minimg": "http://haitao.nosdn1.127.net/d3c18d60f0e54c32af5cf24d18be585b1419662519909i46mer1g10007.png?imageView&thumbnail=35x0&quality=85",
	"discount": "7.4折",
	"free": ""
}, {
	"title": "Jurlique茱莉蔻 柠檬鼠尾草沐浴露 300ml 花本精华 柔滑肌肤",
	"txt": "舒缓净透，平衡水润",
	"price": "169",
	"del": "210",
	"img": "http://pop.nosdn.127.net/2b507a49-0649-4f59-8d5f-42579694652f?imageView&thumbnail=524x0&quality=85",
	"minimg": "http://haitao.nosdn2.127.net/8b99e5ba0d42459aa6d982698dd7d1d51419662720539i46mj1ui10010.png?imageView&thumbnail=35x0&quality=85",
	"discount": "8.1折",
	"free": ""
}, {
	"title": "【日本直邮】SAINT LAURENT PARIS 圣罗兰 经典百搭男士名片夹375949-bxre6-1077",
	"txt": "经典百搭",
	"price": "889",
	"del": "2241",
	"img": "http://pop.nosdn.127.net/20d67325-9fb9-4742-aea7-bec89aef68cf.jpg?imageView&thumbnail=524x0&quality=85",
	"minimg": "http://haitao.nosdn1.127.net/d3c18d60f0e54c32af5cf24d18be585b1419662519909i46mer1g10007.png?imageView&thumbnail=35x0&quality=85",
	"discount": "4.0折",
	"free": ""
}, {
	"title": "【日本直邮】HUNTING WORLD 男士休闲简约单肩挎包 7209-435",
	"txt": "休闲简约",
	"price": "3139",
	"del": "4662",
	"img": "http://pop.nosdn.127.net/46e19c87-01dc-4f50-94e5-e987e210ae67.jpg?imageView&thumbnail=524x0&quality=85",
	"minimg": "http://haitao.nos.netease.com/1077833fa2854dcb97502084f24f449d1419659976324i46kw8bh10001.png?imageView&thumbnail=35x0&quality=85",
	"discount": "6.8折",
	"free": ""
}, {
	"title": "【日本直邮】THREE DOTS 男士纯棉圆领短袖T恤",
	"txt": "舒适休闲 潮流时尚",
	"price": "419",
	"del": "636",
	"img": "http://pop.nosdn.127.net/6329fb52-e22f-4fd8-9fa1-b281dc2f87e6.jpg?imageView&thumbnail=524x0&quality=85",
	"minimg": "http://haitao.nos.netease.com/1077833fa2854dcb97502084f24f449d1419659976324i46kw8bh10001.png?imageView&thumbnail=35x0&quality=85",
	"discount": "6.6折",
	"free": ""
}, {
	"title": "HOLA赫拉 玫瑰平衡补水系列眼霜 28g 滋养眼周 淡化细纹",
	"txt": "补水锁水，改善肌肤干燥",
	"price": "155",
	"del": "188",
	"img": "http://pop.nosdn.127.net/65b8b7fc-de87-4af7-a792-4c85babdfe94?imageView&thumbnail=524x0&quality=85",
	"minimg": "http://haitao.nosdn2.127.net/8b99e5ba0d42459aa6d982698dd7d1d51419662720539i46mj1ui10010.png?imageView&thumbnail=35x0&quality=85",
	"discount": "8.3折",
	"free": ""
}, {
	"title": "Jurlique茱莉蔻 玫瑰护手乳霜 40ml 深层滋养 无惧空调房",
	"txt": "补水，细腻滋养",
	"price": "109",
	"del": "209",
	"img": "http://pop.nosdn.127.net/fbe3f711-0971-42d0-8440-d66dc74dc5b8?imageView&thumbnail=524x0&quality=85",
	"minimg": "http://haitao.nosdn2.127.net/8b99e5ba0d42459aa6d982698dd7d1d51419662720539i46mj1ui10010.png?imageView&thumbnail=35x0&quality=85",
	"discount": "5.3折",
	"free": ""
}]